sm64_random_assets/__init__.py
sm64_random_assets/__main__.py
sm64_random_assets/bootstrap/__init__.py
sm64_random_assets/bootstrap/build_asset_metadata.py
sm64_random_assets/cli/__init__.py
sm64_random_assets/cli/__main__.py
sm64_random_assets/cli/generate.py
sm64_random_assets/cli/grab_baserom.py
sm64_random_assets/debug/__init__.py
sm64_random_assets/debug/comparison.py
sm64_random_assets/generators/__init__.py
sm64_random_assets/generators/audio_generator.py
sm64_random_assets/generators/binary_generator.py
sm64_random_assets/generators/image_generator.py
sm64_random_assets/rc/__init__.py
sm64_random_assets/rc/asset_metadata.json
sm64_random_assets/rc/registry.py
sm64_random_assets/util/__init__.py
sm64_random_assets/util/util_pattern.py
sm64_random_assets/util/util_random.py
sm64_random_assets/util/util_yaml.py
sm64_random_assets/vendor/__init__.py
sm64_random_assets/vendor/aifc.py
sm64_random_assets-0.1.1.dist-info/METADATA
sm64_random_assets-0.1.1.dist-info/WHEEL
sm64_random_assets-0.1.1.dist-info/entry_points.txt
sm64_random_assets-0.1.1.dist-info/top_level.txt
sm64_random_assets-0.1.1.dist-info/RECORD
